{
  "version": 1,
  "functions": {
    "/api/cron/enrich-complexes": {
      "maxDuration": 300
    },
    "/api/cron/fetch-bank-rates": {
      "maxDuration": 60
    },
    "/api/cron/fetch-rates": {
      "maxDuration": 60
    },
    "/api/cron/fetch-reb-index": {
      "maxDuration": 120
    },
    "/api/cron/fetch-rents": {
      "maxDuration": 300
    },
    "/api/cron/fetch-transactions": {
      "maxDuration": 300
    },
    "/api/cron/generate-cardnews": {
      "maxDuration": 60
    },
    "/api/cron/generate-report": {
      "maxDuration": 60
    },
    "/api/cron/generate-seeding": {
      "maxDuration": 60
    },
    "/api/cron/geocode-complexes": {
      "maxDuration": 300
    },
    "/api/cron/post-instagram": {
      "maxDuration": 60
    },
    "/api/cron/send-push": {
      "maxDuration": 60
    },
    "/api/cron/validate-data": {
      "maxDuration": 300
    },
    "/apt/[region]/[slug]/opengraph-image": {},
    "/opengraph-image": {}
  }
}